jsmaps/__init__.py
jsmaps/main.py
jsmaps-0.1.2.dist-info/WHEEL
jsmaps-0.1.2.dist-info/METADATA
jsmaps-0.1.2.dist-info/RECORD
